rokucli/__init__.py
rokucli/cli.py
rokucli/discover.py
rokucli-1.0.6.dist-info/LICENSE
rokucli-1.0.6.dist-info/METADATA
rokucli-1.0.6.dist-info/WHEEL
rokucli-1.0.6.dist-info/entry_points.txt
rokucli-1.0.6.dist-info/top_level.txt
rokucli-1.0.6.dist-info/RECORD
