Metadata-Version: 2.1
Name: rokucli
Version: 1.0.6
Summary: Command-line control of your Roku device
Home-page: https://github.com/ncmiller/roku-cli
Author: Nick Miller
Author-email: nick.miller.83@gmail.com
License: MIT
Keywords: roku cli
Platform: any
Classifier: Development Status :: 3 - Alpha
Classifier: Intended Audience :: Developers
Classifier: License :: OSI Approved :: MIT License
Classifier: Topic :: Multimedia
Classifier: Natural Language :: English
Classifier: Operating System :: OS Independent
Classifier: Programming Language :: Python
License-File: LICENSE
Requires-Dist: roku (>=3.0)
Requires-Dist: blessed
Requires-Dist: future
